examples/skid_buffer/src/skid_buffer.sv
// Code your design here
`default_nettype none 

module skid_buffer
# (
  parameter n = 5, nb = n * 8
)
(
  input  wire             aclk,
  input  wire             aresetn,

  input  wire [nb - 1:0]  in_tdata,
  input  wire             in_tvalid,
  output reg              in_tready,

  output reg [nb - 1:0]   out_tdata,
  output reg              out_tvalid,
  input  reg              out_tready
);


logic [1:0]         state; // 10 - empty, 11 - half, 01 - full
logic [nb-1:0]      buf_tdata;

logic               is_write;
logic               is_read;

assign  is_write    = in_tvalid & in_tready;
assign  is_read     = out_tvalid & out_tready;

assign in_tready    = state[1];
assign out_tvalid   = state[0];


always_ff @(posedge aclk) begin

    if( is_write )
        buf_tdata <= #1 in_tdata;

    case( state )
        2'b10: begin // empty: in_tready=1, out_tvalid=0
            out_tdata <= #1 in_tdata;
            if( is_write ) begin
                state <= #1 2'b11;
            end
        end

        2'b11: begin // half: in_tready=1, out_tvalid=1
            case( {is_write, is_read })
                2'b01: begin  // read
                        state <= #1 2'b10;
                end

                2'b10: begin   // write
                        state <= #1 2'b01;
                end

                2'b11: begin   // write & read
                    out_tdata <= #1 in_tdata;
                end
            endcase

        end

        2'b01: begin    // full: in_tready=0, out_tvalid=1
               if( is_read ) begin
                   state <= #1 2'b11;
                   out_tdata <= #1 buf_tdata;
               end 
        end

    endcase

    if( ~aresetn ) begin
        state <= 2'b10;
    end 
end
  
endmodule

`default_nettype wire

examples/skid_buffer/src/testbench.sv
// Code your testbench here
// or browse Examples

`default_nettype none

module tb
  ();
  
  string	test_name[1:0]=
  {
   "randomize", 
   "direct" 
  };
  
task test_finish;
  		input int 	test_id;
  		input string	test_name;
  		input int		result;
begin
  automatic int fd = $fopen( "global.txt", "a" );
  
  if( 1==result ) begin
    $fdisplay( fd, "test_id=%-5d test_name: %15s         TEST_PASSED", test_id, test_name );
    $display( "test_id=%-5d test_name: %15s         TEST_PASSED", test_id, test_name );
  end else begin
    $fdisplay( fd, "test_id=%-5d test_name: %15s         TEST_FAILED *******", test_id, test_name );
    $display( "test_id=%-5d test_name: %15s         TEST_FAILED *******", test_id, test_name );
  end
  
  $stop();
end endtask  
  
localparam  n = 4, nb = n * 8;
localparam  maxkeep = 2**n;

logic              aclk=0;
logic              aresetn;

logic [nb - 1:0]   in_tdata='0;
logic              in_tvalid='0;
logic              in_tready;

logic [nb - 1:0]   expect_tdata;
logic [nb - 1:0]   out_tdata;
logic              out_tvalid;
logic              out_tready='1;
  
int                 cnt_wr=0;
int                 cnt_rd=0;
int                 cnt_ok=0;  
int                 cnt_error=0;

int                 test_id=0;
logic               test_start=0;
logic               test_timeout=0;
logic               test_done=0;
int                 out_ready_cnt=0;

logic [7:0]         q_data  [$];

  

initial begin
  $dumpfile("dump.vcd");
  $dumpvars(1);
end
always #5 aclk = ~aclk;
  
skid_buffer  
#(
  .n    ( n )
)
 uut
(
          .*
);


task write_data;
    input logic [nb - 1:0]    data;
    input int                 pause;  // 0 - tvalid still high
begin
      in_tdata  <= #1 data;
      in_tvalid <= #1 '1;

      for( int ii=n-1; ii>=0; ii-- )
            q_data.push_front( data[(ii)*8+:8]);

      @(posedge aclk iff in_tvalid & in_tready);
      cnt_wr++;
      if( cnt_wr<16 ) begin
        $display( "input: %s  (%h) ", data, data, );
      end

      if( pause>0 ) begin
        in_tvalid <= #1 '0;
        in_tdata  <= #1 '0;
        for( int ii=0; ii<pause; ii++ )
          @(posedge aclk);
      end

end endtask


task write_seq;
begin
  automatic logic [7:0]       data_out=8'h41;
  automatic logic [nb*2-1:0]  val;
  automatic int               pause;

  //while(1) begin
    for( int jj=0; jj<500; jj++ ) begin

      pause = $urandom_range( 0, 3 );

      for( int ii=0; ii<n*2; ii++ ) begin
        val[ii*8+:8] = data_out;
        data_out++;
        if( 8'h5B==data_out )
          data_out=8'h41;

      end
      write_data( val, pause );
    end 
  //   if( 100==$get_coverage())
  //     break;
  // end

  test_done=1;

end endtask

task set_outready_cnt;
      input int cnt;
begin
      out_tready <= #1 '0;
      out_ready_cnt = cnt;

end endtask

task gen_out_tready;
begin

  automatic int cnt_high;
  automatic int cnt_low;
  while(1) begin

    cnt_high = $urandom_range( 0, 6 );
    cnt_low  = $urandom_range( 1, 6 );

    @(posedge aclk iff out_tready);

    if( test_done )
      break;

    if( cnt_high ) begin
        repeat(cnt_high) @(posedge aclk);
    end
    set_outready_cnt( cnt_low );

  end
  
end endtask

always @(posedge aclk)
  if( out_ready_cnt>0 ) begin
      out_ready_cnt--;
      if( 0==out_ready_cnt )
        out_tready <= #1 '1;
  end



always @(posedge aclk)
  if( out_tvalid & out_tready ) begin
    for( int ii=n-1; ii>=0; ii--) begin
      expect_tdata[ii*8+:8] = q_data.pop_back();
    end

    if( expect_tdata==out_tdata ) begin
      cnt_ok++;

      if( cnt_ok<16 )
        $display( "output: %s  (%h)  ok: %-5d error: %-5d  - Ok", out_tdata, out_tdata, cnt_ok, cnt_error );
    end else begin
      cnt_error++;
      if( cnt_error<16 )
        $display( "output: %s  (%h)  expect %s (%h) ok: %-5d error: %-5d  - Error", out_tdata, out_tdata, expect_tdata, expect_tdata, cnt_ok, cnt_error );

    end

    cnt_rd++;
  end

initial begin

  @(posedge aclk iff test_start=='1);

  case( test_id )
  0: begin
      $display("Test 0: %s", test_name[0]);

            @(posedge aclk);

            write_data( "0123", 0 );
            write_data( "4567", 0 );
            write_data( "89ab", 1 );
            #500;

            set_outready_cnt( 4 );
            write_data( "0123", 0 );
            write_data( "4567", 0 );
            set_outready_cnt( 4 );
            write_data( "89ab", 1 );
            #500;

            write_data( "0123", 1 );
            write_data( "4567", 1 );
            write_data( "89ab", 1 );

            test_done=1;



  end
  1: begin
      $display("Test 1: %s", test_name[1]);
      fork
          write_seq();
          gen_out_tready();
      join
  end
  endcase

end 

initial begin
    #100000;
    $display( "Timeout");
    test_timeout = '1;
end

initial begin  
//   int fd = $fopen("test_id.txt", "r");
//   $fscanf( fd,"%d\n",test_id);
//   $fclose(fd );

  int args=-1;
   
  if( $value$plusargs( "test_id=%0d", args )) begin
    if( args>=0 && args<2 )
      test_id = args;

    $display( "args=%d  test_id=%d", args, test_id );

  end


  $display("Test gearbox_packing test_id=%d  name:", test_id, test_name[test_id] );
  
  aresetn = '0;

  #100;

  aresetn = '1;

  @(posedge aclk );
  test_start = '1;

  @(posedge aclk iff test_done=='1 || test_timeout=='1);

  if( test_timeout )
    cnt_error++;

  $display( "cnt_wr: %d", cnt_wr );
  $display( "cnt_rd: %d", cnt_rd );
  $display( "cnt_ok: %d", cnt_ok );
  $display( "cnt_error: %d", cnt_error );


  // $display("overall coverage = %0f", $get_coverage());
  // $display("coverage of covergroup cg = %0f", uut.cg.get_coverage());
  // $display("coverage of covergroup cg.in_tready = %0f", uut.cg.in_tready.get_coverage());
  // $display("coverage of covergroup cg.in_tvalid = %0f", uut.cg.in_tvalid.get_coverage());
  // $display("coverage of covergroup cg.out_tready = %0f", uut.cg.out_tready.get_coverage());
  // $display("coverage of covergroup cg.out_tvalid = %0f", uut.cg.out_tvalid.get_coverage());
  // $display("coverage of covergroup cg.flag_hf = %0f", uut.cg.flag_hf.get_coverage());
  
  // $display("coverage of covergroup cg.i_vld_rdy = %0f", uut.cg.i_vld_rdy.get_coverage());
  // $display("coverage of covergroup cg.o_vld_rdy = %0f", uut.cg.o_vld_rdy.get_coverage());

  // $display("coverage of covergroup cg.o_rdy_transitions = %0f", uut.cg.o_rdy_transitions.get_coverage());
  

  if( 0==cnt_error && cnt_ok>0 )
    test_finish( test_id, test_name[test_id], 1 );  // test passed
  else
    test_finish( test_id, test_name[test_id], 0 );  // test failed



end

endmodule

`default_nettype wire

examples/skid_buffer/vivado/dump.vcd
$date
   Sat Sep 11 17:42:43 2021
$end
$version
  2020.2
$end
$timescale
  1ps
$end
$scope module tb $end
$var reg 1 ! aclk $end
$var reg 1 " aresetn $end
$var reg 32 # in_tdata [31:0] $end
$var reg 1 $ in_tvalid $end
$var reg 1 % in_tready $end
$var reg 32 & expect_tdata [31:0] $end
$var reg 32 ' out_tdata [31:0] $end
$var reg 1 ( out_tvalid $end
$var reg 1 ) out_tready $end
$var reg 32 * cnt_wr $end
$var reg 32 + cnt_rd $end
$var reg 32 , cnt_ok $end
$var reg 32 - cnt_error $end
$var reg 32 . test_id $end
$var reg 1 / test_start $end
$var reg 1 0 test_timeout $end
$var reg 1 1 test_done $end
$var reg 32 2 out_ready_cnt $end
$var reg 32 3 q_data $end
$upscope $end
$enddefinitions $end
#0
$dumpvars
0!
0"
b0 #
0$
x%
bx &
bx '
x(
1)
b0 *
b0 +
b0 ,
b0 -
b1 .
0/
00
01
b0 2
b0 3
$end
#5000
1!
1%
0(
#10000
0!
#15000
1!
#16000
b0 '
#20000
0!
#25000
1!
#26000
b0 '
#30000
0!
#35000
1!
#36000
b0 '
#40000
0!
#45000
1!
#46000
b0 '
#50000
0!
#55000
1!
#56000
b0 '
#60000
0!
#65000
1!
#66000
b0 '
#70000
0!
#75000
1!
#76000
b0 '
#80000
0!
#85000
1!
#86000
b0 '
#90000
0!
#95000
1!
#96000
b0 '
#100000
0!
1"
#105000
1!
1/
#106000
b1000100010000110100001001000001 #
1$
b0 '
#110000
0!
#115000
1!
b1 *
#116000
b1001100010010110100101001001001 #
1$
b1000100010000110100001001000001 '
1(
#120000
0!
#125000
1!
b1000100010000110100001001000001 &
b10 *
b1 +
b1 ,
#126000
b0 #
0$
b1001100010010110100101001001001 '
#130000
0!
#135000
1!
b1001100010010110100101001001001 &
b10 +
b10 ,
#136000
0(
#140000
0!
#145000
1!
#146000
b0 '
#150000
0!
#155000
1!
b0 2
#156000
b1010100010100110101001001010001 #
1$
b0 '
1)
#160000
0!
#165000
1!
b11 *
#166000
b0 #
0$
b1010100010100110101001001010001 '
1(
#170000
0!
#175000
1!
b1010100010100110101001001010001 &
b11 +
b11 ,
#176000
0(
#180000
0!
#185000
1!
#186000
b1000010010000010101101001011001 #
1$
b0 '
#190000
0!
#195000
1!
b100 *
#196000
b1001010010010010100100001000111 #
1$
b1000010010000010101101001011001 '
1(
#200000
0!
#205000
1!
b1000010010000010101101001011001 &
b101 *
b100 +
b100 ,
b10 2
#206000
b0 #
0$
b1001010010010010100100001000111 '
0)
#210000
0!
#215000
1!
b1 2
#216000
b1010010010100010101000001001111 #
1$
#220000
0!
#225000
1!
b110 *
b0 2
#226000
b0 #
0$
0%
1)
#230000
0!
#235000
1!
b1001010010010010100100001000111 &
b101 +
b101 ,
#236000
b1011010010110010101100001010111 #
1$
1%
b1010010010100010101000001001111 '
#240000
0!
#245000
1!
b1010010010100010101000001001111 &
b111 *
b110 +
b110 ,
#246000
b0 #
0$
b1011010010110010101100001010111 '
#250000
0!
#255000
1!
b1011010010110010101100001010111 &
b111 +
b111 ,
#256000
0(
#260000
0!
#265000
1!
#266000
b0 '
#270000
0!
#275000
1!
#276000
b1001000010001110100011001000101 #
1$
b0 '
#280000
0!
#285000
1!
b1000 *
b101 2
#286000
b0 #
0$
b1001000010001110100011001000101 '
1(
0)
#290000
0!
#295000
1!
b100 2
#296000
b1010000010011110100111001001101 #
1$
#300000
0!
#305000
1!
b1001 *
b11 2
#306000
b1011000010101110101011001010101 #
1$
0%
#310000
0!
#315000
1!
b10 2
#320000
0!
#325000
1!
b1 2
#330000
0!
#335000
1!
b0 2
#336000
1)
#340000
0!
#345000
1!
b1001000010001110100011001000101 &
b1000 +
b1000 ,
b10 2
#346000
1%
b1010000010011110100111001001101 '
0)
#350000
0!
#355000
1!
b1010 *
b1 2
#356000
b1000110010001010100010001000011 #
1$
0%
#360000
0!
#365000
1!
b0 2
#366000
1)
#370000
0!
#375000
1!
b1010000010011110100111001001101 &
b1001 +
b1001 ,
#376000
1%
b1011000010101110101011001010101 '
#380000
0!
#385000
1!
b1011000010101110101011001010101 &
b1011 *
b1010 +
b1010 ,
#386000
b0 #
0$
b1000110010001010100010001000011 '
#390000
0!
#395000
1!
b1000110010001010100010001000011 &
b1011 +
b1011 ,
#396000
0(
#400000
0!
#405000
1!
#406000
b1001110010011010100110001001011 #
1$
b0 '
#410000
0!
#415000
1!
b1100 *
#416000
b0 #
0$
b1001110010011010100110001001011 '
1(
#420000
0!
#425000
1!
b1001110010011010100110001001011 &
b1100 +
b1100 ,
#426000
0(
#430000
0!
#435000
1!
b11 2
#436000
b0 '
0)
#440000
0!
#445000
1!
b10 2
#446000
b1010110010101010101010001010011 #
1$
b0 '
#450000
0!
#455000
1!
b1101 *
b1 2
#456000
b1000100010000110100001001000001 #
1$
b1010110010101010101010001010011 '
1(
#460000
0!
#465000
1!
b1110 *
b0 2
#466000
b0 #
0$
0%
1)
#470000
0!
#475000
1!
b1010110010101010101010001010011 &
b1101 +
b1101 ,
#476000
b1001100010010110100101001001001 #
1$
1%
b1000100010000110100001001000001 '
#480000
0!
#485000
1!
b1000100010000110100001001000001 &
b1111 *
b1110 +
b1110 ,
#486000
b0 #
0$
b1001100010010110100101001001001 '
#490000
0!
#495000
1!
b1001100010010110100101001001001 &
b1111 +
b1111 ,
#496000
b1010100010100110101001001010001 #
1$
0(
#500000
0!
#505000
1!
b10000 *
#506000
b0 #
0$
b1010100010100110101001001010001 '
1(
#510000
0!
#515000
1!
b1010100010100110101001001010001 &
b10000 +
b10000 ,
b0 2
#516000
0(
1)
#520000
0!
#525000
1!
#526000
b1000010010000010101101001011001 #
1$
b0 '
#530000
0!
#535000
1!
b10001 *
#536000
b1001010010010010100100001000111 #
1$
b1000010010000010101101001011001 '
1(
#540000
0!
#545000
1!
b1000010010000010101101001011001 &
b10010 *
b10001 +
b10001 ,
#546000
b0 #
0$
b1001010010010010100100001000111 '
#550000
0!
#555000
1!
b1001010010010010100100001000111 &
b10010 +
b10010 ,
#556000
b1010010010100010101000001001111 #
1$
0(
#560000
0!
#565000
1!
b10011 *
b100 2
#566000
b0 #
0$
b1010010010100010101000001001111 '
1(
0)
#570000
0!
#575000
1!
b11 2
#580000
0!
#585000
1!
b10 2
#586000
b1011010010110010101100001010111 #
1$
#590000
0!
#595000
1!
b10100 *
b1 2
#596000
b0 #
0$
0%
#600000
0!
#605000
1!
b0 2
#606000
1)
#610000
0!
#615000
1!
b1010010010100010101000001001111 &
b10011 +
b10011 ,
#616000
1%
b1011010010110010101100001010111 '
#620000
0!
#625000
1!
b1011010010110010101100001010111 &
b10100 +
b10100 ,
#626000
b1001000010001110100011001000101 #
1$
0(
#630000
0!
#635000
1!
b10101 *
#636000
b0 #
0$
b1001000010001110100011001000101 '
1(
#640000
0!
#645000
1!
b1001000010001110100011001000101 &
b10101 +
b10101 ,
b1 2
#646000
b1010000010011110100111001001101 #
1$
0(
0)
#650000
0!
#655000
1!
b10110 *
b0 2
#656000
b0 #
0$
b1010000010011110100111001001101 '
1(
1)
#660000
0!
#665000
1!
b1010000010011110100111001001101 &
b10110 +
b10110 ,
#666000
0(
#670000
0!
#675000
1!
#676000
b0 '
#680000
0!
#685000
1!
#686000
b1011000010101110101011001010101 #
1$
b0 '
#690000
0!
#695000
1!
b10111 *
#696000
b1000110010001010100010001000011 #
1$
b1011000010101110101011001010101 '
1(
#700000
0!
#705000
1!
b1011000010101110101011001010101 &
b11000 *
b10111 +
b10111 ,
#706000
b0 #
0$
b1000110010001010100010001000011 '
#710000
0!
#715000
1!
b1000110010001010100010001000011 &
b11000 +
b11000 ,
#716000
0(
#720000
0!
#725000
1!
b101 2
#726000
b0 '
0)
#730000
0!
#735000
1!
b100 2
#736000
b1001110010011010100110001001011 #
1$
b0 '
#740000
0!
#745000
1!
b11001 *
b11 2
#746000
b0 #
0$
b1001110010011010100110001001011 '
1(
#750000
0!
#755000
1!
b10 2
#760000
0!
#765000
1!
b1 2
#766000
b1010110010101010101010001010011 #
1$
#770000
0!
#775000
1!
b11010 *
b0 2
#776000
b0 #
0$
0%
1)
#780000
0!
#785000
1!
b1001110010011010100110001001011 &
b11001 +
b11001 ,
#786000
1%
b1010110010101010101010001010011 '
#790000
0!
#795000
1!
b1010110010101010101010001010011 &
b11010 +
b11010 ,
b101 2
#796000
b1000100010000110100001001000001 #
1$
0(
0)
#800000
0!
#805000
1!
b11011 *
b100 2
#806000
b0 #
0$
b1000100010000110100001001000001 '
1(
#810000
0!
#815000
1!
b11 2
#816000
b1001100010010110100101001001001 #
1$
#820000
0!
#825000
1!
b11100 *
b10 2
#826000
b0 #
0$
0%
#830000
0!
#835000
1!
b1 2
#840000
0!
#845000
1!
b0 2
#846000
1)
#850000
0!
#855000
1!
b1000100010000110100001001000001 &
b11011 +
b11011 ,
b10 2
#856000
b1010100010100110101001001010001 #
1$
1%
b1001100010010110100101001001001 '
0)
#860000
0!
#865000
1!
b11101 *
b1 2
#866000
b0 #
0$
0%
#870000
0!
#875000
1!
b0 2
#876000
1)
#880000
0!
#885000
1!
b1001100010010110100101001001001 &
b11100 +
b11100 ,
#886000
b1000010010000010101101001011001 #
1$
1%
b1010100010100110101001001010001 '
#890000
0!
#895000
1!
b1010100010100110101001001010001 &
b11110 *
b11101 +
b11101 ,
#896000
b1001010010010010100100001000111 #
1$
b1000010010000010101101001011001 '
#900000
0!
#905000
1!
b1000010010000010101101001011001 &
b11111 *
b11110 +
b11110 ,
#906000
b0 #
0$
b1001010010010010100100001000111 '
#910000
0!
#915000
1!
b1001010010010010100100001000111 &
b11111 +
b11111 ,
#916000
b1010010010100010101000001001111 #
1$
0(
#920000
0!
#925000
1!
b100000 *
#926000
b0 #
0$
b1010010010100010101000001001111 '
1(
#930000
0!
#935000
1!
b1010010010100010101000001001111 &
b100000 +
b100000 ,
b1 2
#936000
0(
0)
#940000
0!
#945000
1!
b0 2
#946000
b0 '
1)
#950000
0!
#955000
1!
#956000
b1011010010110010101100001010111 #
1$
b0 '
#960000
0!
#965000
1!
b100001 *
#966000
b0 #
0$
b1011010010110010101100001010111 '
1(
#970000
0!
#975000
1!
b1011010010110010101100001010111 &
b100001 +
b100001 ,
#976000
0(
#980000
0!
#985000
1!
#986000
b0 '
#990000
0!
#995000
1!
#996000
b1001000010001110100011001000101 #
1$
b0 '
#1000000
0!
#1005000
1!
b100010 *
#1006000
b0 #
0$
b1001000010001110100011001000101 '
1(
#1010000
0!
#1015000
1!
b1001000010001110100011001000101 &
b100010 +
b100010 ,
b101 2
#1016000
0(
0)
#1020000
0!
#1025000
1!
b100 2
#1026000
b1010000010011110100111001001101 #
1$
b0 '
#1030000
0!
#1035000
1!
b100011 *
b11 2
#1036000
b0 #
0$
b1010000010011110100111001001101 '
1(
#1040000
0!
#1045000
1!
b10 2
#1046000
b1011000010101110101011001010101 #
1$
#1050000
0!
#1055000
1!
b100100 *
b1 2
#1056000
b0 #
0$
0%
#1060000
0!
#1065000
1!
b0 2
#1066000
b1000110010001010100010001000011 #
1$
1)
#1070000
0!
#1075000
1!
b1010000010011110100111001001101 &
b100011 +
b100011 ,
#1076000
1%
b1011000010101110101011001010101 '
#1080000
0!
#1085000
1!
b1011000010101110101011001010101 &
b100101 *
b100100 +
b100100 ,
#1086000
b0 #
0$
b1000110010001010100010001000011 '
#1090000
0!
#1095000
1!
b1000110010001010100010001000011 &
b100101 +
b100101 ,
b100 2
#1096000
b1001110010011010100110001001011 #
1$
0(
0)
#1100000
0!
#1105000
1!
b100110 *
b11 2
#1106000
b0 #
0$
b1001110010011010100110001001011 '
1(
#1110000
0!
#1115000
1!
b10 2
#1120000
0!
#1125000
1!
b1 2
#1130000
0!
#1135000
1!
b0 2
#1136000
b1010110010101010101010001010011 #
1$
1)
#1140000
0!
#1145000
1!
b1001110010011010100110001001011 &
b100111 *
b100110 +
b100110 ,
#1146000
b0 #
0$
b1010110010101010101010001010011 '
#1150000
0!
#1155000
1!
b1010110010101010101010001010011 &
b100111 +
b100111 ,
#1156000
b1000100010000110100001001000001 #
1$
0(
#1160000
0!
#1165000
1!
b101000 *
#1166000
b0 #
0$
b1000100010000110100001001000001 '
1(
#1170000
0!
#1175000
1!
b1000100010000110100001001000001 &
b101000 +
b101000 ,
#1176000
b1001100010010110100101001001001 #
1$
0(
#1180000
0!
#1185000
1!
b101001 *
#1186000
b1010100010100110101001001010001 #
1$
b1001100010010110100101001001001 '
1(
#1190000
0!
#1195000
1!
b1001100010010110100101001001001 &
b101010 *
b101001 +
b101001 ,
#1196000
b0 #
0$
b1010100010100110101001001010001 '
#1200000
0!
#1205000
1!
b1010100010100110101001001010001 &
b101010 +
b101010 ,
b101 2
#1206000
0(
0)
#1210000
0!
#1215000
1!
b100 2
#1216000
b1000010010000010101101001011001 #
1$
b0 '
#1220000
0!
#1225000
1!
b101011 *
b11 2
#1226000
b0 #
0$
b1000010010000010101101001011001 '
1(
#1230000
0!
#1235000
1!
b10 2
#1236000
b1001010010010010100100001000111 #
1$
#1240000
0!
#1245000
1!
b101100 *
b1 2
#1246000
b0 #
0$
0%
#1250000
0!
#1255000
1!
b0 2
#1256000
1)
#1260000
0!
#1265000
1!
b1000010010000010101101001011001 &
b101011 +
b101011 ,
b0 2
#1266000
b1010010010100010101000001001111 #
1$
1%
b1001010010010010100100001000111 '
1)
#1270000
0!
#1275000
1!
b1001010010010010100100001000111 &
b101101 *
b101100 +
b101100 ,
#1276000
b0 #
0$
b1010010010100010101000001001111 '
#1280000
0!
#1285000
1!
b1010010010100010101000001001111 &
b101101 +
b101101 ,
#1286000
b1011010010110010101100001010111 #
1$
0(
#1290000
0!
#1295000
1!
b101110 *
#1296000
b0 #
0$
b1011010010110010101100001010111 '
1(
#1300000
0!
#1305000
1!
b1011010010110010101100001010111 &
b101110 +
b101110 ,
b1 2
#1306000
0(
0)
#1310000
0!
#1315000
1!
b0 2
#1316000
b1001000010001110100011001000101 #
1$
b0 '
1)
#1320000
0!
#1325000
1!
b101111 *
#1326000
b0 #
0$
b1001000010001110100011001000101 '
1(
#1330000
0!
#1335000
1!
b1001000010001110100011001000101 &
b101111 +
b101111 ,
#1336000
b1010000010011110100111001001101 #
1$
0(
#1340000
0!
#1345000
1!
b110000 *
b100 2
#1346000
b0 #
0$
b1010000010011110100111001001101 '
1(
0)
#1350000
0!
#1355000
1!
b11 2
#1360000
0!
#1365000
1!
b10 2
#1370000
0!
#1375000
1!
b1 2
#1376000
b1011000010101110101011001010101 #
1$
#1380000
0!
#1385000
1!
b110001 *
b0 2
#1386000
b0 #
0$
0%
1)
#1390000
0!
#1395000
1!
b1010000010011110100111001001101 &
b110000 +
b110000 ,
#1396000
b1000110010001010100010001000011 #
1$
1%
b1011000010101110101011001010101 '
#1400000
0!
#1405000
1!
b1011000010101110101011001010101 &
b110010 *
b110001 +
b110001 ,
#1406000
b0 #
0$
b1000110010001010100010001000011 '
#1410000
0!
#1415000
1!
b1000110010001010100010001000011 &
b110010 +
b110010 ,
b100 2
#1416000
0(
0)
#1420000
0!
#1425000
1!
b11 2
#1426000
b1001110010011010100110001001011 #
1$
b0 '
#1430000
0!
#1435000
1!
b110011 *
b10 2
#1436000
b0 #
0$
b1001110010011010100110001001011 '
1(
#1440000
0!
#1445000
1!
b1 2
#1446000
b1010110010101010101010001010011 #
1$
#1450000
0!
#1455000
1!
b110100 *
b0 2
#1456000
b0 #
0$
0%
1)
#1460000
0!
#1465000
1!
b1001110010011010100110001001011 &
b110011 +
b110011 ,
#1466000
b1000100010000110100001001000001 #
1$
1%
b1010110010101010101010001010011 '
#1470000
0!
#1475000
1!
b1010110010101010101010001010011 &
b110101 *
b110100 +
b110100 ,
#1476000
b1001100010010110100101001001001 #
1$
b1000100010000110100001001000001 '
#1480000
0!
#1485000
1!
b1000100010000110100001001000001 &
b110110 *
b110101 +
b110101 ,
#1486000
b0 #
0$
b1001100010010110100101001001001 '
#1490000
0!
#1495000
1!
b1001100010010110100101001001001 &
b110110 +
b110110 ,
#1496000
0(
#1500000
0!
#1505000
1!
#1506000
b0 '
#1510000
0!
#1515000
1!
#1516000
b1010100010100110101001001010001 #
1$
b0 '
#1520000
0!
#1525000
1!
b110111 *
b10 2
#1526000
b0 #
0$
b1010100010100110101001001010001 '
1(
0)
#1530000
0!
#1535000
1!
b1 2
#1540000
0!
#1545000
1!
b0 2
#1546000
1)
#1550000
0!
#1555000
1!
b1010100010100110101001001010001 &
b110111 +
b110111 ,
#1556000
b1000010010000010101101001011001 #
1$
0(
#1560000
0!
#1565000
1!
b111000 *
#1566000
b0 #
0$
b1000010010000010101101001011001 '
1(
#1570000
0!
#1575000
1!
b1000010010000010101101001011001 &
b111000 +
b111000 ,
#1576000
b1001010010010010100100001000111 #
1$
0(
#1580000
0!
#1585000
1!
b111001 *
#1586000
b0 #
0$
b1001010010010010100100001000111 '
1(
#1590000
0!
#1595000
1!
b1001010010010010100100001000111 &
b111001 +
b111001 ,
#1596000
0(
#1600000
0!
#1605000
1!
#1606000
b1010010010100010101000001001111 #
1$
b0 '
#1610000
0!
#1615000
1!
b111010 *
b1 2
#1616000
b0 #
0$
b1010010010100010101000001001111 '
1(
0)
#1620000
0!
#1625000
1!
b0 2
#1626000
1)
#1630000
0!
#1635000
1!
b1010010010100010101000001001111 &
b111010 +
b111010 ,
b11 2
#1636000
b1011010010110010101100001010111 #
1$
0(
0)
#1640000
0!
#1645000
1!
b111011 *
b10 2
#1646000
b0 #
0$
b1011010010110010101100001010111 '
1(
#1650000
0!
#1655000
1!
b1 2
#1660000
0!
#1665000
1!
b0 2
#1666000
b1001000010001110100011001000101 #
1$
1)
#1670000
0!
#1675000
1!
b1011010010110010101100001010111 &
b111100 *
b111011 +
b111011 ,
#1676000
b0 #
0$
b1001000010001110100011001000101 '
#1680000
0!
#1685000
1!
b1001000010001110100011001000101 &
b111100 +
b111100 ,
#1686000
b1010000010011110100111001001101 #
1$
0(
#1690000
0!
#1695000
1!
b111101 *
#1696000
b0 #
0$
b1010000010011110100111001001101 '
1(
#1700000
0!
#1705000
1!
b1010000010011110100111001001101 &
b111101 +
b111101 ,
#1706000
0(
#1710000
0!
#1715000
1!
#1716000
b0 '
#1720000
0!
#1725000
1!
b11 2
#1726000
b1011000010101110101011001010101 #
1$
b0 '
0)
#1730000
0!
#1735000
1!
b111110 *
b10 2
#1736000
b0 #
0$
b1011000010101110101011001010101 '
1(
#1740000
0!
#1745000
1!
b1 2
#1750000
0!
#1755000
1!
b0 2
#1756000
b1000110010001010100010001000011 #
1$
1)
#1760000
0!
#1765000
1!
b1011000010101110101011001010101 &
b111111 *
b111110 +
b111110 ,
#1766000
b1001110010011010100110001001011 #
1$
b1000110010001010100010001000011 '
#1770000
0!
#1775000
1!
b1000110010001010100010001000011 &
b1000000 *
b111111 +
b111111 ,
#1776000
b0 #
0$
b1001110010011010100110001001011 '
#1780000
0!
#1785000
1!
b1001110010011010100110001001011 &
b1000000 +
b1000000 ,
#1786000
b1010110010101010101010001010011 #
1$
0(
#1790000
0!
#1795000
1!
b1000001 *
#1796000
b0 #
0$
b1010110010101010101010001010011 '
1(
#1800000
0!
#1805000
1!
b1010110010101010101010001010011 &
b1000001 +
b1000001 ,
b0 2
#1806000
0(
1)
#1810000
0!
#1815000
1!
#1816000
b0 '
#1820000
0!
#1825000
1!
#1826000
b1000100010000110100001001000001 #
1$
b0 '
#1830000
0!
#1835000
1!
b1000010 *
#1836000
b0 #
0$
b1000100010000110100001001000001 '
1(
#1840000
0!
#1845000
1!
b1000100010000110100001001000001 &
b1000010 +
b1000010 ,
#1846000
0(
#1850000
0!
#1855000
1!
#1856000
b1001100010010110100101001001001 #
1$
b0 '
#1860000
0!
#1865000
1!
b1000011 *
b101 2
#1866000
b0 #
0$
b1001100010010110100101001001001 '
1(
0)
#1870000
0!
#1875000
1!
b100 2
#1880000
0!
#1885000
1!
b11 2
#1886000
b1010100010100110101001001010001 #
1$
#1890000
0!
#1895000
1!
b1000100 *
b10 2
#1896000
b0 #
0$
0%
#1900000
0!
#1905000
1!
b1 2
#1906000
b1000010010000010101101001011001 #
1$
#1910000
0!
#1915000
1!
b0 2
#1916000
1)
#1920000
0!
#1925000
1!
b1001100010010110100101001001001 &
b1000011 +
b1000011 ,
#1926000
1%
b1010100010100110101001001010001 '
#1930000
0!
#1935000
1!
b1010100010100110101001001010001 &
b1000101 *
b1000100 +
b1000100 ,
#1936000
b0 #
0$
b1000010010000010101101001011001 '
#1940000
0!
#1945000
1!
b1000010010000010101101001011001 &
b1000101 +
b1000101 ,
#1946000
0(
#1950000
0!
#1955000
1!
#1956000
b0 '
#1960000
0!
#1965000
1!
#1966000
b1001010010010010100100001000111 #
1$
b0 '
#1970000
0!
#1975000
1!
b1000110 *
#1976000
b0 #
0$
b1001010010010010100100001000111 '
1(
#1980000
0!
#1985000
1!
b1001010010010010100100001000111 &
b1000110 +
b1000110 ,
b11 2
#1986000
0(
0)
#1990000
0!
#1995000
1!
b10 2
#1996000
b1010010010100010101000001001111 #
1$
b0 '
#2000000
0!
#2005000
1!
b1000111 *
b1 2
#2006000
b0 #
0$
b1010010010100010101000001001111 '
1(
#2010000
0!
#2015000
1!
b0 2
#2016000
1)
#2020000
0!
#2025000
1!
b1010010010100010101000001001111 &
b1000111 +
b1000111 ,
#2026000
b1011010010110010101100001010111 #
1$
0(
#2030000
0!
#2035000
1!
b1001000 *
#2036000
b0 #
0$
b1011010010110010101100001010111 '
1(
#2040000
0!
#2045000
1!
b1011010010110010101100001010111 &
b1001000 +
b1001000 ,
#2046000
0(
#2050000
0!
#2055000
1!
#2056000
b1001000010001110100011001000101 #
1$
b0 '
#2060000
0!
#2065000
1!
b1001001 *
b101 2
#2066000
b0 #
0$
b1001000010001110100011001000101 '
1(
0)
#2070000
0!
#2075000
1!
b100 2
#2080000
0!
#2085000
1!
b11 2
#2086000
b1010000010011110100111001001101 #
1$
#2090000
0!
#2095000
1!
b1001010 *
b10 2
#2096000
b0 #
0$
0%
